databricks/__init__.py
databricks/labs/__init__.py
databricks/labs/pytester/__about__.py
databricks/labs/pytester/__init__.py
databricks/labs/pytester/py.typed
databricks/labs/pytester/fixtures/__init__.py
databricks/labs/pytester/fixtures/baseline.py
databricks/labs/pytester/fixtures/catalog.py
databricks/labs/pytester/fixtures/compute.py
databricks/labs/pytester/fixtures/connect.py
databricks/labs/pytester/fixtures/environment.py
databricks/labs/pytester/fixtures/iam.py
databricks/labs/pytester/fixtures/ml.py
databricks/labs/pytester/fixtures/permissions.py
databricks/labs/pytester/fixtures/plugin.py
databricks/labs/pytester/fixtures/redash.py
databricks/labs/pytester/fixtures/secrets.py
databricks/labs/pytester/fixtures/sql.py
databricks/labs/pytester/fixtures/unwrap.py
databricks/labs/pytester/fixtures/watchdog.py
databricks/labs/pytester/fixtures/workspace.py
tests/resources/hatchling-whl/src/hatchling_whl/__about__.py
tests/resources/hatchling-whl/src/hatchling_whl/__init__.py
databricks_labs_pytester-0.7.4.dist-info/METADATA
databricks_labs_pytester-0.7.4.dist-info/WHEEL
databricks_labs_pytester-0.7.4.dist-info/entry_points.txt
databricks_labs_pytester-0.7.4.dist-info/licenses/LICENSE
databricks_labs_pytester-0.7.4.dist-info/licenses/NOTICE
databricks_labs_pytester-0.7.4.dist-info/RECORD
