Metadata-Version: 2.4
Name: databricks-labs-pytester
Version: 0.7.4
Summary: Python Testing for Databricks
Project-URL: Issues, https://github.com/databrickslabs/pytester/issues
Project-URL: Source, https://github.com/databrickslabs/pytester
Author-email: Serge Smertin <serge.smertin@databricks.com>, Vuong Nguyen <vuong.nguyen@databricks.com>, Marcin Wojtyczka <marcin.wojtyczka@databricks.com>, Ziyuan Qin <ziyuan.qin@databricks.com>, William Conti <william.conti@databricks.com>, Lars George <lars.george@databricks.com>, Cor Zuurmond <cor.zuurmond@databricks.com>, Andrew Snare <andrew.snare@databricks.com>, Liran Bareket <liran.bareket@databricks.com>, Pritish Pai <pritish.pai@databricks.com>
Maintainer-email: Serge Smertin <serge.smertin@databricks.com>
License-File: LICENSE
License-File: NOTICE
Keywords: Databricks,pytest
Classifier: Development Status :: 4 - Beta
Classifier: Environment :: Console
Classifier: Framework :: Pytest
Classifier: Intended Audience :: Developers
Classifier: Intended Audience :: System Administrators
Classifier: License :: Other/Proprietary License
Classifier: Operating System :: MacOS
Classifier: Operating System :: Microsoft :: Windows
Classifier: Programming Language :: Python
Classifier: Programming Language :: Python :: 3.10
Classifier: Programming Language :: Python :: 3.11
Classifier: Programming Language :: Python :: 3.12
Classifier: Programming Language :: Python :: Implementation :: CPython
Classifier: Topic :: Software Development :: Libraries
Classifier: Topic :: Utilities
Requires-Python: >=3.10
Requires-Dist: databricks-labs-lsql>=0.10
Requires-Dist: databricks-sdk<1.0,>=0.51.0
Requires-Dist: pytest>=8.3
